PID_pendulum/PID_control.py
PID_pendulum/__init__.py
PID_pendulum/conf.py
PID_pendulum/debug.py
PID_pendulum-0.0.13.dist-info/DESCRIPTION.rst
PID_pendulum-0.0.13.dist-info/METADATA
PID_pendulum-0.0.13.dist-info/RECORD
PID_pendulum-0.0.13.dist-info/WHEEL
PID_pendulum-0.0.13.dist-info/metadata.json
PID_pendulum-0.0.13.dist-info/top_level.txt
