Metadata-Version: 2.0
Name: PID-pendulum
Version: 0.0.13
Summary: A PID pendulum controller.
Home-page: https://github.com/PhilippSchuette/PID_pendulum
Author: Philipp Schuette
Author-email: p.schuette@online.de
License: GPLv3
Download-URL: https://pypi.python.org/pypi/PID-pendulum
Platform: UNKNOWN
Classifier: Programming Language :: Python :: 3
Classifier: License :: OSI Approved :: GNU General Public License v3 (GPLv3)
Classifier: Operating System :: OS Independent
Requires-Dist: matplotlib
Requires-Dist: numpy
